sinorstack/__init__.py
sinorstack/_template/.gitignore
sinorstack/_template/src/__init__.py
sinorstack/_template/src/adapters/__init__.py
sinorstack/_template/src/application/__init__.py
sinorstack/_template/src/application/containers.py
sinorstack/_template/src/application/exceptions.py
sinorstack/_template/src/application/settings.py
sinorstack/_template/src/domain/__init__.py
sinorstack/_template/src/domain/interfaces/__init__.py
sinorstack/_template/src/domain/use_cases/__init__.py
sinorstack/_template/src/entrypoint.py
sinorstack/_template/src/infrastructure/__init__.py
sinorstack/_template/src/infrastructure/database/__init__.py
sinorstack/_template/src/infrastructure/repositories/__init__.py
sinorstack/_template/src/presentors/__init__.py
sinorstack/_template/src/presentors/controllers/__init__.py
sinorstack/_template/tests/__init__.py
sinorstack/cli.py
sinorstack/controllers.py
sinorstack/drf/__init__.py
sinorstack/drf/decorators.py
sinorstack-0.3.0.dist-info/METADATA
sinorstack-0.3.0.dist-info/WHEEL
sinorstack-0.3.0.dist-info/entry_points.txt
sinorstack-0.3.0.dist-info/RECORD
