Metadata-Version: 2.3
Name: sinorstack
Version: 0.3.0
Summary: 
Author: shept
Author-email: github@sinortax.ru
Requires-Python: >=3.12
Classifier: Programming Language :: Python :: 3
Classifier: Programming Language :: Python :: 3.12
Classifier: Programming Language :: Python :: 3.13
Requires-Dist: copier (>=9.5.0,<10.0.0)
Requires-Dist: dependency-injector (>=4.46.0,<5.0.0)
Requires-Dist: pydantic (>=2.10.6,<3.0.0)
Requires-Dist: typer (>=0.15.2,<0.16.0)
